[   
    {
        "picture":"https://ehaoyao.oss-cn-hangzhou.aliyuncs.com/2018/1/23/1516692757238_48.jpg"
    },
    {
        "des":"欧姆龙",
        "title":"欧姆龙血压计 家用上臂式血压仪HEM-7052 电子血压计",
        "price":"￥329",
        "picture":"https://ehaoyao.oss-cn-hangzhou.aliyuncs.com/2018/4/25/1524648719972_29.png"
    },
    {
        "des":"汤臣倍健",
        "title":"【买一送一 送原品】汤臣倍健 液体钙软胶囊成人补钙 100粒",
        "price":"￥88",
        "picture":"https://ehaoyao.oss-cn-hangzhou.aliyuncs.com/2018/1/23/1516692858822_26.png"
    },
    {
        "des":" 鸿茅",
        "title":"鸿茅药酒 500ml ",
        "price":"￥298",
        "picture":"https://ehaoyao.oss-cn-hangzhou.aliyuncs.com/2018/1/23/1516692922299_53.png"
    },
    {
        "des":"恒瑞",
        "title":"恒瑞 非布司他片 40mg*10片",
        "price":"￥99",
        "picture":"https://ehaoyao.oss-cn-hangzhou.aliyuncs.com/2018/1/23/1516692964668_43.png"
    },
    {
        "picture":"https://ehaoyao.oss-cn-hangzhou.aliyuncs.com/2018/1/23/1516692757238_48.jpg"      
    }

]